pytest_crate/plugin.py
pytest_crate-0.3.0.dist-info/LICENSE
pytest_crate-0.3.0.dist-info/METADATA
pytest_crate-0.3.0.dist-info/WHEEL
pytest_crate-0.3.0.dist-info/entry_points.txt
pytest_crate-0.3.0.dist-info/top_level.txt
pytest_crate-0.3.0.dist-info/RECORD
